qwgraph-1.0.2.dist-info/METADATA
qwgraph-1.0.2.dist-info/WHEEL
qwgraph-1.0.2.dist-info/licenses/LICENSE
qwgraph/coins.py
qwgraph/__pycache__/__init__.cpython-310.pyc
qwgraph/__pycache__/qwsearch.cpython-310.pyc
qwgraph/pipelines.py
qwgraph/qwsearch.py
qwgraph/__init__.py
qwgraph/qwgraph.cpython-39-aarch64-linux-gnu.so
qwgraph-1.0.2.dist-info/RECORD
