Metadata-Version: 2.4
Name: qwgraph
Version: 1.0.2
Requires-Dist: numpy>=1.23.5
Requires-Dist: pandas>=1.5.1
Requires-Dist: matplotlib>=3.5.1
Requires-Dist: networkx>=3.0
Requires-Dist: tqdm>=4.64.1
License-File: LICENSE
